lager_trio_websocket/__init__.py
lager_trio_websocket/_impl.py
lager_trio_websocket/_version.py
lager_trio_websocket-0.9.0.dev0.dist-info/LICENSE
lager_trio_websocket-0.9.0.dev0.dist-info/METADATA
lager_trio_websocket-0.9.0.dev0.dist-info/WHEEL
lager_trio_websocket-0.9.0.dev0.dist-info/top_level.txt
lager_trio_websocket-0.9.0.dev0.dist-info/RECORD
