Metadata-Version: 2.1
Name: lager-trio-websocket
Version: 0.9.0.dev0
Summary: WebSocket library for Trio
Home-page: https://github.com/HyperionGray/trio-websocket
Author: Mark E. Haase
Author-email: mehaase@gmail.com
License: UNKNOWN
Project-URL: Bug Reports, https://github.com/lagerdata/trio-websocket/issues
Project-URL: Source, https://github.com/lagerdata/trio-websocket
Keywords: websocket client server trio
Platform: UNKNOWN
Classifier: Development Status :: 3 - Alpha
Classifier: Intended Audience :: Developers
Classifier: Topic :: Software Development :: Libraries
Classifier: License :: OSI Approved :: MIT License
Classifier: Programming Language :: Python :: 3.6
Classifier: Programming Language :: Python :: 3.7
Classifier: Programming Language :: Python :: 3.8
Classifier: Programming Language :: Python :: Implementation :: CPython
Classifier: Programming Language :: Python :: Implementation :: PyPy
Requires-Python: >=3.6
Requires-Dist: async-generator (<2,>=1.10)
Requires-Dist: ipaddress (<2,>=1.0.22)
Requires-Dist: trio (>=0.11)
Requires-Dist: wsproto (<0.15,>=0.14)
Requires-Dist: yarl (<2,>=1.2.6)
